LICENSE
MANIFEST.in
README.md
requirements.txt
setup.cfg
setup.py
tests/__init__.py
tests/test_client.py
tests/test_models.py
transferwise/__init__.py
transferwise/utils.py
transferwise/client/__init__.py
transferwise/client/client.py
transferwise/client/config.py
transferwise/models/__init__.py
transferwise/models/account.py
transferwise/models/base.py
transferwise/models/fund.py
transferwise/models/profile.py
transferwise/models/quote.py
transferwise/models/transfer.py
transferwise_python_sdk.egg-info/PKG-INFO
transferwise_python_sdk.egg-info/SOURCES.txt
transferwise_python_sdk.egg-info/dependency_links.txt
transferwise_python_sdk.egg-info/requires.txt
transferwise_python_sdk.egg-info/top_level.txt