Metadata-Version: 2.1
Name: transferwise-python-sdk
Version: 0.0.2
Summary: A light TransferWise SDK for Python
Home-page: https://github.com/davidvartanian/transferwise-python-sdk
Author: David Vartanian
Author-email: davidvartanian@posteo.de
License: gpl-3.0
Download-URL: https://github.com/davidvartanian/transferwise-python-sdk/archive/v0.0.2.tar.gz
Platform: UNKNOWN
Classifier: Programming Language :: Python :: 3
Classifier: License :: OSI Approved :: GNU General Public License v3 (GPLv3)
Classifier: Operating System :: OS Independent
Requires-Python: >=3.6
